Metadata-Version: 1.1
Name: excludedwordslint
Version: 0.1.0
Summary: Don't use X word in your documentation!
Home-page: https://github.com/dgarcia360/excludedwords-lint
Author: David Garcia
Author-email: dgarcia360@outlook.com
License: BSD
Platform: any
Classifier: Development Status :: 4 - Beta
Classifier: Environment :: Console
Classifier: Intended Audience :: Developers
Classifier: License :: OSI Approved :: BSD License
Classifier: Operating System :: POSIX
Classifier: Operating System :: MacOS
Classifier: Operating System :: Unix
Classifier: Operating System :: Microsoft :: Windows
Classifier: Programming Language :: Python
Classifier: Programming Language :: Python :: 2
Classifier: Programming Language :: Python :: 3
Classifier: Topic :: Software Development :: Libraries :: Python Modules
